{
    "rootpath": "..",
    "modules": [
        {
            "path": "base/Node.zig",
            "ignore": [
                "NodePool",
                "NodeID",
                "NodeEntry",
                "NodeType",
                "registerNodePool",
                "getType",
                "findType"
            ]
        },
        {
            "path": "base/Transform.zig"
        },
        {
            "path": "input/Input.zig"
        },
        {
            "path": "input/InputMap.zig"
        }
    ]
}